zet/__init__.py
zet/editor_commands.py
zet/git_commands.py
zet/main.py
zet/repo.py
zet/settings.py
zet/zet.py
zet_cli-0.0.1.dist-info/LICENSE
zet_cli-0.0.1.dist-info/METADATA
zet_cli-0.0.1.dist-info/WHEEL
zet_cli-0.0.1.dist-info/entry_points.txt
zet_cli-0.0.1.dist-info/top_level.txt
zet_cli-0.0.1.dist-info/RECORD
