Metadata-Version: 2.1
Name: zet-cli
Version: 0.0.1
Summary: A Zettlekasten CLI implementation.
Home-page: https://github.com/mattdood/zet-cli
Author: Matthew Wimberly
Author-email: matthew.wimb@gmail.com
Project-URL: Bug Tracker, https://github.com/mattdood/zet-cli/issues
Keywords: notes,notetaking,note management
Platform: unix
Platform: linux
Platform: osx
Platform: cygwin
Platform: win32
Classifier: Programming Language :: Python :: 3
Classifier: License :: OSI Approved :: MIT License
Classifier: Operating System :: OS Independent
Requires-Python: >=3.6
License-File: LICENSE
Provides-Extra: testing
Requires-Dist: pytest ; extra == 'testing'
